{
  "project_info": {
    "project_number": "87959149639",
    "firebase_url": "https://tested-me.firebaseio.com",
    "project_id": "tested-me",
    "storage_bucket": "tested-me.appspot.com"
  },
  "client": [
    {
      "client_info": {
        "mobilesdk_app_id": "1:87959149639:android:72d2a152bb110191fea562",
        "android_client_info": {
          "package_name": "com.tested.me"
        }
      },
      "oauth_client": [
        {
          "client_id": "87959149639-r69aefdg6guv9c8f60lhtvnslt27en6a.apps.googleusercontent.com",
          "client_type": 1,
          "android_info": {
            "package_name": "com.tested.me",
            "certificate_hash": "5e8f16062ea3cd2c4a0d547876baa6f38cabf625"
          }
        },
        {
          "client_id": "87959149639-7i8gogq17m0jm9vpujqcllkh7odj8364.apps.googleusercontent.com",
          "client_type": 3
        }
      ],
      "api_key": [
        {
          "current_key": "AIzaSyAS0g0YrEEuKVXqEYIWLbjIH5ihvkOmRuU"
        }
      ],
      "services": {
        "appinvite_service": {
          "other_platform_oauth_client": [
            {
              "client_id": "87959149639-7i8gogq17m0jm9vpujqcllkh7odj8364.apps.googleusercontent.com",
              "client_type": 3
            },
            {
              "client_id": "87959149639-n3r8n7h5abgln142fks68g3gqqoh1fqu.apps.googleusercontent.com",
              "client_type": 2,
              "ios_info": {
                "bundle_id": "com.tested.me.production",
                "app_store_id": "1523785240"
              }
            }
          ]
        }
      }
    },
    {
      "client_info": {
        "mobilesdk_app_id": "1:87959149639:android:643cb6d32df8b4bdfea562",
        "android_client_info": {
          "package_name": "com.tested.me.production"
        }
      },
      "oauth_client": [
        {
          "client_id": "87959149639-7i8gogq17m0jm9vpujqcllkh7odj8364.apps.googleusercontent.com",
          "client_type": 3
        }
      ],
      "api_key": [
        {
          "current_key": "AIzaSyAS0g0YrEEuKVXqEYIWLbjIH5ihvkOmRuU"
        }
      ],
      "services": {
        "appinvite_service": {
          "other_platform_oauth_client": [
            {
              "client_id": "87959149639-7i8gogq17m0jm9vpujqcllkh7odj8364.apps.googleusercontent.com",
              "client_type": 3
            },
            {
              "client_id": "87959149639-n3r8n7h5abgln142fks68g3gqqoh1fqu.apps.googleusercontent.com",
              "client_type": 2,
              "ios_info": {
                "bundle_id": "com.tested.me.production",
                "app_store_id": "1523785240"
              }
            }
          ]
        }
      }
    },
    {
      "client_info": {
        "mobilesdk_app_id": "1:87959149639:android:c50fb0d506a3c68cfea562",
        "android_client_info": {
          "package_name": "com.tested.me.staging"
        }
      },
      "oauth_client": [
        {
          "client_id": "87959149639-7i8gogq17m0jm9vpujqcllkh7odj8364.apps.googleusercontent.com",
          "client_type": 3
        }
      ],
      "api_key": [
        {
          "current_key": "AIzaSyAS0g0YrEEuKVXqEYIWLbjIH5ihvkOmRuU"
        }
      ],
      "services": {
        "appinvite_service": {
          "other_platform_oauth_client": [
            {
              "client_id": "87959149639-7i8gogq17m0jm9vpujqcllkh7odj8364.apps.googleusercontent.com",
              "client_type": 3
            },
            {
              "client_id": "87959149639-n3r8n7h5abgln142fks68g3gqqoh1fqu.apps.googleusercontent.com",
              "client_type": 2,
              "ios_info": {
                "bundle_id": "com.tested.me.production",
                "app_store_id": "1523785240"
              }
            }
          ]
        }
      }
    }
  ],
  "configuration_version": "1"
}